django_utils/__init__.py
django_utils/constants.py
django_utils/cache/__init__.py
django_utils/fields/__init__.py
django_utils/fields/related_fields.py
django_utils/fields/tuple_field.py
django_utils/models/__init__.py
django_utils/models/base.py
django_utils/models/lookup.py
django_utils/models/queryset.py
django_utils/mongo_ext/__init__.py
django_utils/mongo_ext/transactions.py
django_extension-0.1.0.dist-info/METADATA
django_extension-0.1.0.dist-info/WHEEL
django_extension-0.1.0.dist-info/top_level.txt
django_extension-0.1.0.dist-info/RECORD
