Metadata-Version: 2.4
Name: django-extension
Version: 0.1.0
Summary: Add your description here
Requires-Python: >=3.11
Requires-Dist: django>=5.2.2
Requires-Dist: pymongo>=4.13.0
Requires-Dist: ruff>=0.11.13
Requires-Dist: shelve-cache>=0.0.4
